nanoflow/__init__.py
nanoflow/core/__init__.py
nanoflow/core/engine.py
nanoflow/io/__init__.py
nanoflow/io/loader.py
nanoflow/utils/__init__.py
nanoflow/utils/downloader.py
nanoflow/utils/memory.py
nanoflow_z-1.2.4.dist-info/METADATA
nanoflow_z-1.2.4.dist-info/WHEEL
nanoflow_z-1.2.4.dist-info/top_level.txt
nanoflow_z-1.2.4.dist-info/RECORD
