Metadata-Version: 2.4
Name: nanoflow-Z
Version: 1.2.4
Summary: NanoFlow: Zero-RAM (Max 1.5GB) Engine
Home-page: https://github.com/Zousko/nanoflow
Author: Zousko
Requires-Dist: torch
Requires-Dist: transformers
Requires-Dist: safetensors
Requires-Dist: huggingface_hub
Requires-Dist: psutil
Requires-Dist: requests
Requires-Dist: tqdm
Dynamic: author
Dynamic: home-page
Dynamic: requires-dist
Dynamic: summary
